setup.py
develia/__init__.py
develia/functions2.py
develia_test.egg-info/PKG-INFO
develia_test.egg-info/SOURCES.txt
develia_test.egg-info/dependency_links.txt
develia_test.egg-info/top_level.txt